MANIFEST.in
README.md
rrdtool_cffi.py
setup.py
rrdtool_cffi.egg-info/PKG-INFO
rrdtool_cffi.egg-info/SOURCES.txt
rrdtool_cffi.egg-info/dependency_links.txt
rrdtool_cffi.egg-info/requires.txt
rrdtool_cffi.egg-info/top_level.txt