Metadata-Version: 1.0
Name: rrdtool-cffi
Version: 0.1
Summary: Bindings for rrdtool via cffi
Home-page: https://github.com/stephan-hof/rrdtool_cffi
Author: Stephan Hofmockel
Author-email: Use the github issues
License: UNKNOWN
Keywords: rrdtool cffi
Platform: UNKNOWN
